picsellia_collectstatic/__init__.py
picsellia_collectstatic/apps.py
picsellia_collectstatic/management/__init__.py
picsellia_collectstatic/management/commands/__init__.py
picsellia_collectstatic/management/commands/picsellia_collectstatic.py
picsellia_collectstatic-0.0.4.dist-info/LICENSE
picsellia_collectstatic-0.0.4.dist-info/METADATA
picsellia_collectstatic-0.0.4.dist-info/WHEEL
picsellia_collectstatic-0.0.4.dist-info/RECORD
