Metadata-Version: 2.1
Name: picsellia-collectstatic
Version: 0.0.4
Summary: Optimized collectstatic for S3ManifestStaticStorage
Home-page: https://github.com/picselliahq/s3manifestcollectstatic
License: MIT
Keywords: django,collectstatic,S3,manifest
Author: Thomas Darget
Author-email: thomas.darget@picsellia.com
Requires-Python: >=3.8,<4.0
Classifier: Environment :: Web Environment
Classifier: Framework :: Django
Classifier: Intended Audience :: Developers
Classifier: License :: OSI Approved :: MIT License
Classifier: Programming Language :: Python
Classifier: Programming Language :: Python :: 3
Classifier: Programming Language :: Python :: 3.8
Classifier: Programming Language :: Python :: 3.9
Classifier: Programming Language :: Python :: 3.10
Classifier: Programming Language :: Python :: 3.11
Classifier: Programming Language :: Python :: 3.6
Classifier: Programming Language :: Python :: 3.7
Requires-Dist: Django (>=4.0,<5.0)
Project-URL: Repository, https://github.com/picselliahq/s3manifestcollectstatic
